ds_connector_service/__init__.py
ds_connector_service/api/__init__.py
ds_connector_service/api/contracts_api.py
ds_connector_service/api/data_products_api.py
ds_connector_service/api/health_api.py
ds_connector_service/api/monitoring_api.py
ds_connector_service/api/transactions_api.py
ds_connector_service/api_client.py
ds_connector_service/api_response.py
ds_connector_service/configuration.py
ds_connector_service/docs/ContractsApi.md
ds_connector_service/docs/DataProductsApi.md
ds_connector_service/docs/HealthApi.md
ds_connector_service/docs/HTTPValidationError.md
ds_connector_service/docs/MonitoringApi.md
ds_connector_service/docs/TransactionsApi.md
ds_connector_service/docs/ValidationError.md
ds_connector_service/docs/ValidationErrorLocInner.md
ds_connector_service/exceptions.py
ds_connector_service/models/__init__.py
ds_connector_service/models/http_validation_error.py
ds_connector_service/models/validation_error.py
ds_connector_service/models/validation_error_loc_inner.py
ds_connector_service/py.typed
ds_connector_service/rest.py
ds_connector_service/test/__init__.py
ds_connector_service/test/test_contracts_api.py
ds_connector_service/test/test_data_products_api.py
ds_connector_service/test/test_health_api.py
ds_connector_service/test/test_http_validation_error.py
ds_connector_service/test/test_monitoring_api.py
ds_connector_service/test/test_transactions_api.py
ds_connector_service/test/test_validation_error.py
ds_connector_service/test/test_validation_error_loc_inner.py
ds_connector_client-0.1.0.dist-info/LICENSE
ds_connector_client-0.1.0.dist-info/METADATA
ds_connector_client-0.1.0.dist-info/WHEEL
ds_connector_client-0.1.0.dist-info/RECORD
