Metadata-Version: 2.3
Name: ds-connector-client
Version: 0.1.0
Summary: Python client for Connector Service API
License: MIT
Keywords: OpenAPI,Connector Service API,Client
Author: HIRO-MicroDataCenters
Author-email: all-hiro@hiro-microdatacenters.nl
Requires-Python: >=3.10,<4.0
Classifier: License :: OSI Approved :: MIT License
Classifier: Programming Language :: Python :: 3
Classifier: Programming Language :: Python :: 3.10
Classifier: Programming Language :: Python :: 3.11
Classifier: Programming Language :: Python :: 3.12
Classifier: Programming Language :: Python :: 3.13
Requires-Dist: pydantic (>=2)
Requires-Dist: python-dateutil (>=2.8.2)
Requires-Dist: typing-extensions (>=4.7.1)
Requires-Dist: urllib3 (>=1.25.3)
